LICENSE
MANIFEST.in
README.md
requirements.txt
setup.py
src/diffusers_interpret/__init__.py
src/diffusers_interpret/attribution.py
src/diffusers_interpret/data.py
src/diffusers_interpret/explainer.py
src/diffusers_interpret/generated_images.py
src/diffusers_interpret/pixel_attributions.py
src/diffusers_interpret/saliency_map.py
src/diffusers_interpret/token_attributions.py
src/diffusers_interpret/utils.py
src/diffusers_interpret.egg-info/PKG-INFO
src/diffusers_interpret.egg-info/SOURCES.txt
src/diffusers_interpret.egg-info/dependency_links.txt
src/diffusers_interpret.egg-info/requires.txt
src/diffusers_interpret.egg-info/top_level.txt
src/diffusers_interpret/dataviz/image-slider/index.html
src/diffusers_interpret/dataviz/image-slider/css/index.css
src/diffusers_interpret/dataviz/image-slider/js/index.js
src/diffusers_interpret/explainers/__init__.py
src/diffusers_interpret/explainers/latent_diffusion.py
src/diffusers_interpret/explainers/stable_diffusion.py