Metadata-Version: 2.1
Name: diffusers-interpret
Version: 0.5.0
Summary: diffusers-interpret: model explainability for 🤗 Diffusers
Home-page: https://github.com/JoaoLages/diffusers-interpret
Author: Joao Lages
Author-email: joaop.glages@gmail.com
License: MIT
License-File: LICENSE
